SFDCFW/Access.py
SFDCFW/Constant.py
SFDCFW/SFDCFW.py
SFDCFW/SObject.py
SFDCFW/__init__.py
SFDCFW/Common/Email.py
SFDCFW/Common/__init__.py
SFDCFW/Rest/Bulk.py
SFDCFW/Rest/Query.py
SFDCFW/Rest/Rest.py
SFDCFW/Rest/SObject.py
SFDCFW/Rest/Tooling.py
SFDCFW/Rest/User.py
SFDCFW/Rest/__init__.py
SFDCFW/Soap/CustomField.py
SFDCFW/Soap/Metadata.py
SFDCFW/Soap/ValidationRule.py
SFDCFW/Soap/WorkflowRule.py
SFDCFW/Soap/__init__.py
SFDCFW/Test/TestAccess.py
SFDCFW/Test/TestMetadata.py
SFDCFW/Test/TestRestQuery.py
SFDCFW/Test/TestRestSObjectAccount.py
SFDCFW/Test/__init__.py
sfdcfw-0.1.5.dist-info/LICENSE
sfdcfw-0.1.5.dist-info/METADATA
sfdcfw-0.1.5.dist-info/WHEEL
sfdcfw-0.1.5.dist-info/top_level.txt
sfdcfw-0.1.5.dist-info/RECORD
