Metadata-Version: 2.1
Name: sfdcfw
Version: 0.1.5
Summary: Saleforce.com FrameWork.
Author: Yan Kuang
Author-email: YTKme@Outlook.com
License: UNKNOWN
Keywords: salesforce sfdc fw api
Platform: UNKNOWN
Classifier: Programming Language :: Python :: 3
Classifier: License :: OSI Approved :: GNU General Public License v3 or later (GPLv3+)
Classifier: Operating System :: OS Independent
Requires-Python: >=3.5
License-File: LICENSE
Requires-Dist: pandas
Requires-Dist: requests
Requires-Dist: zeep
